{
   "area": "Charlottenburg-Wilmersdorf",
   "area_id": "04",
   "source": "http://www.gsi-berlin.info/redirectA.asp?filename=TB0101000004201500.pdf",
   "values": [
      {
         "name": "Bevölkerung",
         "values": [
            {
               "name": "Bevölkerung insgesamt",
               "values": [
                  {
                     "name": "gesamt",
                     "value": 326354,
                     "date": "31.12.2014",
                     "unit": "absolut"
                  },
                  {
                     "name": "männlich",
                     "value": 48.1,
                     "date": "31.12.2014",
                     "unit": "Anteil in %"
                  },
                  {
                     "name": "weiblich",
                     "value": 51.9,
                     "date": "31.12.2014",
                     "unit": "Anteil in %"
                  },
                  {
                     "name": "Migrationshintergrund",
                     "values": [
                        {
                           "name": "gesamt",
                           "value": 36.8,
                           "date": "31.12.2014",
                           "unit": "Anteil in %"
                        },
                        {
                           "name": "mit deutsche Staatsangehörigkeit",
                           "value": 14.9,
                           "date": "31.12.2014",
                           "unit": "Anteil in %"
                        },
                        {
                           "name": "mit ausländischer Staatsangehörigkeit",
                           "value": 21.9,
                           "date": "31.12.2014",
                           "unit": "Anteil in %"
                        }
                     ]
                  }
               ]
            },
            {
               "name": "Bevölkerung nach Altersgruppen",
               "values": [
                  {
                     "name": "0-5",
                     "value": 4.7,
                     "date": "31.12.2013",
                     "unit": "Anteil in %"
                  },
                  {
                     "name": "6-14",
                     "value": 6.4,
                     "date": "31.12.2013",
                     "unit": "Anteil in %"
                  },
                  {
                     "name": "15-17",
                     "value": 2.2,
                     "date": "31.12.2013",
                     "unit": "Anteil in %"
                  },
                  {
                     "name": "18-39",
                     "value": 27.3,
                     "date": "31.12.2013",
                     "unit": "Anteil in %"
                  },
                  {
                     "name": "40-64",
                     "value": 36.7,
                     "date": "31.12.2013",
                     "unit": "Anteil in %"
                  },
                  {
                     "name": "65-74",
                     "value": 13.1,
                     "date": "31.12.2013",
                     "unit": "Anteil in %"
                  },
                  {
                     "name": "75-x",
                     "value": 9.6,
                     "date": "31.12.2013",
                     "unit": "Anteil in %"
                  },
                  {
                     "name": "Jugendquotient",
                     "value": 20.8,
                     "date": "2013",
                     "unit": "0- bis 17-jährige je 100 18- bis 64-jährige"
                  },
                  {
                     "name": "Altenquotient",
                     "value": 35.4,
                     "date": "2013",
                     "unit": "Personen 65 J. u.ä. je 100 18- bis 64-jährige"
                  }
               ]
            },
            {
               "name": "Bevölkerungsprognose",
               "values": [
                  {
                     "name": "0-5",
                     "value": 4.1,
                     "date": "2030",
                     "unit": "Anteil in %"
                  },
                  {
                     "name": "6-14",
                     "value": 6.2,
                     "date": "2030",
                     "unit": "Anteil in %"
                  },
                  {
                     "name": "15-17",
                     "value": 2.1,
                     "date": "2030",
                     "unit": "Anteil in %"
                  },
                  {
                     "name": "18-39",
                     "value": 24.9,
                     "date": "2030",
                     "unit": "Anteil in %"
                  },
                  {
                     "name": "40-64",
                     "value": 35,
                     "date": "2030",
                     "unit": "Anteil in %"
                  },
                  {
                     "name": "65-74",
                     "value": 13.3,
                     "date": "2030",
                     "unit": "Anteil in %"
                  },
                  {
                     "name": "75-x",
                     "value": 14.4,
                     "date": "2030",
                     "unit": "Anteil in %"
                  },
                  {
                     "name": "Jugendquotient",
                     "value": 20.6,
                     "date": "2030",
                     "unit": "0- bis 17-jährige je 100 18- bis 64-jährige"
                  },
                  {
                     "name": "Altenquotient",
                     "value": 46.2,
                     "date": "2030",
                     "unit": "Personen 65 J. u.ä. je 100 18- bis 64-jährige"
                  }
               ]
            },
            {
               "name": "Bevölkerungsentwicklung",
               "values": [
                  {
                     "name": "Lebendgeborene",
                     "value": 2497,
                     "date": "2013",
                     "unit": "absolut"
                  },
                  {
                     "name": "Geborene (außerklinisch)",
                     "value": 269,
                     "date": "2013",
                     "unit": "absolut"
                  },
                  {
                     "name": "Geburtenziffer",
                     "value": 8.3,
                     "date": "2013",
                     "unit": "Lebendgeborene je 1.000 EW"
                  },
                  {
                     "name": "Fruchtbarkeitsziffer",
                     "value": 45.2,
                     "date": "2013",
                     "unit": "Lebendgeborene je 1.000 EW 15- bis 45-j. Frauen"
                  },
                  {
                     "name": "Gestorbene",
                     "value": 3287,
                     "date": "2013",
                     "unit": "absolut"
                  },
                  {
                     "name": "Sterbeziffer",
                     "value": 10.9,
                     "date": "2013",
                     "unit": "Gestorben je 1.000 EW"
                  },
                  {
                     "name": "Geburten- bzw. Sterbeüberschuss",
                     "value": -790,
                     "date": "2013",
                     "unit": "absolut"
                  },
                  {
                     "name": "Wanderungssaldo",
                     "value": 4506,
                     "date": "2013",
                     "unit": "absolut"
                  },
                  {
                     "name": "Bevölkerungszu- oder abnahme",
                     "value": 3746,
                     "date": "2013",
                     "unit": "absolut"
                  }
               ]
            }
         ]
      },
      {
         "name": "Sozioökonomische Lage",
         "values": [
            {
               "name": "Bildungsabschluss (Alter: 18-64 Jahre)",
               "values": [
                  {
                     "name": "Bevölkerung ohne Schulabschluss",
                     "value": 3.7,
                     "date": "2013",
                     "unit": "Anteil in %"
                  },
                  {
                     "name": "Bevölkerung ohne berufl. Ausbildungsabschluss",
                     "value": 23.6,
                     "date": "2013",
                     "unit": "Anteil in %"
                  }
               ]
            },
            {
               "name": "Einpersonenhaushalte",
               "values": [
                  {
                     "name": "gesamt",
                     "value": 59.8,
                     "date": "2013",
                     "unit": "in % aller Haushalte"
                  },
                  {
                     "name": "Einpersonenhaushalte unter 65 J.",
                     "value": 42.1,
                     "date": "2013",
                     "unit": "in % aller Haushalte"
                  },
                  {
                     "name": "Einpersonenhaushalte 65 J. u.ä.",
                     "value": 17.7,
                     "date": "2013",
                     "unit": "in % aller Haushalte"
                  }
               ]
            },
            {
               "name": "Erwerbsstatus",
               "values": [
                  {
                     "name": "Erwerbstätigenquote (15- bis 64-jährige Erwerbstätige an Bevölkerung gleichen Alters)",
                     "value": 69.6,
                     "date": "2013",
                     "unit": "in %"
                  },
                  {
                     "name": "Arbeitslosenquote (Arbeitslose an allen zivilen Erwerbspersonen)",
                     "value": 9.5,
                     "date": "2014",
                     "unit": "in %"
                  }
               ]
            },
            {
               "name": "Einkommen",
               "values": [
                  {
                     "name": "HzL und bedarfsorientierte Grundsicherung außerhalb von Einrichtungen",
                     "value": 26.4,
                     "date": "2014",
                     "unit": "je 1.000 EW"
                  },
                  {
                     "name": "Armutsquote",
                     "value": 14.8,
                     "date": "2014",
                     "unit": "in %"
                  }
               ]
            }
         ]
      },
      {
         "name": "Gesundheitszustand",
         "values": [
            {
               "name": "Lebenserwartung",
               "values": [
                  {
                     "name": "bei Geburt",
                     "values": [
                        {
                           "name": "männlich",
                           "value": 78.9,
                           "date": "2011/13",
                           "unit": "in Jahren"
                        },
                        {
                           "name": "weiblich",
                           "value": 83.5,
                           "date": "2011/13",
                           "unit": "in Jahren"
                        }
                     ]
                  },
                  {
                     "name": "mit 80 Jahren",
                     "values": [
                        {
                           "name": "männlich",
                           "value": 8.2,
                           "date": "2011/13",
                           "unit": "in Jahren"
                        },
                        {
                           "name": "weiblich",
                           "value": 9.9,
                           "date": "2011/13",
                           "unit": "in Jahren"
                        }
                     ]
                  }
               ]
            },
            {
               "name": "Allgemeine Sterblichkeit",
               "values": [
                  {
                     "name": "Gesamtsterblichkeit",
                     "values": [
                        {
                           "name": "gesamt",
                           "value": 521.1,
                           "date": "2011/13",
                           "unit": "je 100.000 DMR"
                        },
                        {
                           "name": "männlich",
                           "value": 643.5,
                           "date": "2011/13",
                           "unit": "je 100.000 DMR"
                        },
                        {
                           "name": "weiblich",
                           "value": 429.8,
                           "date": "2011/13",
                           "unit": "je 100.000 DMR"
                        }
                     ]
                  },
                  {
                     "name": "Vorzeitige Sterblichkeit (0-64 Jahre)",
                     "values": [
                        {
                           "name": "gesamt",
                           "value": 1548,
                           "date": "2011/13",
                           "unit": "absolut"
                        },
                        {
                           "name": "männlich",
                           "value": 213.3,
                           "date": "2011/13",
                           "unit": "je 100.000 DMR"
                        },
                        {
                           "name": "weiblich",
                           "value": 119.5,
                           "date": "2011/13",
                           "unit": "je 100.000 DMR"
                        }
                     ]
                  },
                  {
                     "name": "Sterblichkeit 65 Jahre u.ä.",
                     "values": [
                        {
                           "name": "gesamt",
                           "value": 7881,
                           "date": "2011/13",
                           "unit": "absolut"
                        },
                        {
                           "name": "männlich",
                           "value": 4123.8,
                           "date": "2011/13",
                           "unit": "je 100.000 DMR"
                        },
                        {
                           "name": "weiblich",
                           "value": 2940.1,
                           "date": "2011/13",
                           "unit": "je 100.000 DMR"
                        }
                     ]
                  },
                  {
                     "name": "Perinatale Sterblichkeit",
                     "values": [
                        {
                           "name": "Perinatale Sterblichkeit",
                           "value": 44,
                           "date": "2011/13",
                           "unit": "absolut"
                        },
                        {
                           "name": "Perinatale Sterblichkeit",
                           "value": 5.9,
                           "date": "2011/13",
                           "unit": "je 1.000 Geborene"
                        }
                     ]
                  }
               ]
            },
            {
               "name": "Vermeidbare Sterbefälle",
               "values": [
                  {
                     "name": "Lungenkrebs",
                     "values": [
                        {
                           "name": "gesamt",
                           "value": 196,
                           "date": "2011/13",
                           "unit": "absolut"
                        },
                        {
                           "name": "männlich",
                           "value": 31.2,
                           "date": "2011/13",
                           "unit": "je 100.000 DMR"
                        },
                        {
                           "name": "weiblich",
                           "value": 21.7,
                           "date": "2011/13",
                           "unit": "je 100.000 DMR"
                        }
                     ],
                     "classification": "ICD-10 Nrn.: C33 - C34 / Alter: 15 - 64 Jahre"
                  },
                  {
                     "name": "Ischämiche Herzkrankheiten",
                     "values": [
                        {
                           "name": "gesamt",
                           "value": 106,
                           "date": "2011/13",
                           "unit": "absolut"
                        },
                        {
                           "name": "männlich",
                           "value": 36.3,
                           "date": "2011/13",
                           "unit": "je 100.000 DMR"
                        },
                        {
                           "name": "weiblich",
                           "value": 13.7,
                           "date": "2011/13",
                           "unit": "je 100.000 DMR"
                        }
                     ],
                     "classification": "ICD-10 Nrn.: I20 - I25 / Alter: 35 - 64 Jahre"
                  },
                  {
                     "name": "Akuter Myokardinfarkt",
                     "values": [
                        {
                           "name": "gesamt",
                           "value": 64,
                           "date": "2011/13",
                           "unit": "absolut"
                        },
                        {
                           "name": "männlich",
                           "value": 9.5,
                           "date": "2011/13",
                           "unit": "je 100.000 DMR"
                        },
                        {
                           "name": "weiblich",
                           "value": 3.9,
                           "date": "2011/13",
                           "unit": "je 100.000 DMR"
                        }
                     ],
                     "classification": "ICD-10 Nr: I21 / Alter: 0 - 64 Jahre"
                  },
                  {
                     "name": "Hypertonie und zerebrovaskuläre Krankheiten",
                     "values": [
                        {
                           "name": "gesamt",
                           "value": 55,
                           "date": "2011/13",
                           "unit": "absolut"
                        },
                        {
                           "name": "männlich",
                           "value": 17.2,
                           "date": "2011/13",
                           "unit": "je 100.000 DMR"
                        },
                        {
                           "name": "weiblich",
                           "value": 9.8,
                           "date": "2011/13",
                           "unit": "je 100.000 DMR"
                        }
                     ],
                     "classification": "ICD-10 Nrn.: I10 - I15, I60 - I69 / Alter: 35 - 64 Jahre"
                  },
                  {
                     "name": "Krankheiten der Leber",
                     "values": [
                        {
                           "name": "gesamt",
                           "value": 111,
                           "date": "2011/13",
                           "unit": "absolut"
                        },
                        {
                           "name": "männlich",
                           "value": 18.2,
                           "date": "2011/13",
                           "unit": "je 100.000 DMR"
                        },
                        {
                           "name": "weiblich",
                           "value": 6.4,
                           "date": "2011/13",
                           "unit": "je 100.000 DMR"
                        }
                     ],
                     "classification": "ICD-10 Nrn.: K70 - K77 / Alter: 15 - 74 Jahre"
                  },
                  {
                     "name": "Alkoholische Leberkrankheit",
                     "values": [
                        {
                           "name": "gesamt",
                           "value": 62,
                           "date": "2011/13",
                           "unit": "absolut"
                        },
                        {
                           "name": "männlich",
                           "value": 11,
                           "date": "2011/13",
                           "unit": "je 100.000 DMR"
                        },
                        {
                           "name": "weiblich",
                           "value": 3.3,
                           "date": "2011/13",
                           "unit": "je 100.000 DMR"
                        }
                     ],
                     "classification": "ICD-10 Nr.: K70 / Alter: 15 - 74 Jahre"
                  },
                  {
                     "name": "Bösartige Neubildung der Brustdrüse",
                     "values": [
                        {
                           "name": "gesamt",
                           "value": 68,
                           "date": "2011/13",
                           "unit": "absolut"
                        },
                        {
                           "name": "weiblich",
                           "value": 22.5,
                           "date": "2011/13",
                           "unit": "je 100.000 DMR"
                        }
                     ],
                     "classification": "ICD-10 Nr.: C50 / Alter 25 - 64 Jahre"
                  }
               ]
            },
            {
               "name": "Morbidität",
               "values": [
                  {
                     "name": "Neuerkrankungsrate an bösartigen Neubildungen",
                     "values": [
                        {
                           "name": "männlich",
                           "value": 405,
                           "date": "2010/12",
                           "unit": "je 100.000 DMR"
                        },
                        {
                           "name": "weiblich",
                           "value": 364.7,
                           "date": "2010/12",
                           "unit": "je 100.000 DMR"
                        }
                     ],
                     "classification": "ICD-10 Nr.: C00-C97, ohne C44, mit D09.0, D41.4"
                  },
                  {
                     "name": "Neuerkrankungsrate an tabakassoziierten bösartigen Neubildungen",
                     "values": [
                        {
                           "name": "männlich",
                           "value": 147.7,
                           "date": "2010/12",
                           "unit": "je 100.000 DMR"
                        },
                        {
                           "name": "weiblich",
                           "value": 72.4,
                           "date": "2010/12",
                           "unit": "je 100.000 DMR"
                        }
                     ],
                     "classification": "ICD-10 Nr.: C00-C14, C15, C25, C32, C33-C34. C67, D09.0, D41.4"
                  },
                  {
                     "name": "Pflegebedürftige in ambulanter oder stationärer Pflege",
                     "values": [
                        {
                           "name": "gesamt",
                           "value": 6377,
                           "date": "2013",
                           "unit": "absolut"
                        },
                        {
                           "name": "ambulante Pflege",
                           "value": 1300.3,
                           "date": "2013",
                           "unit": "je 100.000 EW"
                        },
                        {
                           "name": "stationäre Pflege",
                           "value": 809.1,
                           "date": "2013",
                           "unit": "je 100.000 EW"
                        }
                     ]
                  },
                  {
                     "name": "Schwerbehinderte Personen mit Schwb-Ausweis",
                     "values": [
                        {
                           "name": "gesamt",
                           "value": 31454,
                           "date": "2013",
                           "unit": "absolut"
                        },
                        {
                           "name": "männlich",
                           "value": 6604.5,
                           "date": "2013",
                           "unit": "je 100.000 DMR"
                        },
                        {
                           "name": "stationäre Pflege",
                           "value": 6561.5,
                           "date": "2013",
                           "unit": "je 100.000 DMR"
                        }
                     ]
                  },
                  {
                     "name": "Zahnstatus behandlungsbedürftig bei vom ZÄD untersuchten Kindern",
                     "values": [
                        {
                           "name": "3-Jährige",
                           "value": 11.1,
                           "date": "2013/14",
                           "unit": "Anteil in %"
                        },
                        {
                           "name": "6-Jährige",
                           "value": 24.2,
                           "date": "2013/14",
                           "unit": "Anteil in %"
                        },
                        {
                           "name": "12-Jährige",
                           "value": 17.3,
                           "date": "2013/14",
                           "unit": "Anteil in %"
                        }
                     ]
                  },
                  {
                     "name": "Übergewicht (im Rahmen der Einschulungsuntersuchung untersuchte Kinder; mittleres Alter: 5,8 Jahre)",
                     "values": [
                        {
                           "name": "untersuchte Kinder",
                           "value": 2243,
                           "date": "2013",
                           "unit": "absolut"
                        },
                        {
                           "name": "übergewichtig (>90. bis 97. Perzentil)",
                           "value": 5.8,
                           "date": "2013",
                           "unit": "Anteil in %"
                        },
                        {
                           "name": "adipös (>97. Perzentil)",
                           "value": 2.9,
                           "date": "2013",
                           "unit": "Anteil in %"
                        }
                     ]
                  }
               ]
            }
         ]
      },
      {
         "name": "Gesundheitsvorsorge im Kindesalter",
         "values": [
            {
               "name": "Inanspruchnahme des Krankheitsfrüherkennungsprogramms",
               "values": [
                  {
                     "name": "untersuchte Kinder",
                     "value": 2022,
                     "date": "2013",
                     "unit": "absolut"
                  },
                  {
                     "name": "Kinder ohne Dokumentation",
                     "value": 7.7,
                     "date": "2013",
                     "unit": "Anteil in %"
                  },
                  {
                     "name": "Teilnahme an U 8 (Anteil an Einschülern mit Dokumentation)",
                     "value": 95.9,
                     "date": "2013",
                     "unit": "Anteil in %"
                  }
               ]
            },
            {
               "name": "Impfquoten",
               "values": [
                  {
                     "name": "untersuchte Kinder",
                     "value": 2252,
                     "date": "2013",
                     "unit": "absolut"
                  },
                  {
                     "name": "Kinder ohne Impfdokumentation",
                     "value": 10,
                     "date": "2013",
                     "unit": "Anteil in %"
                  },
                  {
                     "name": "Impfquoten 2. Masernimpf. bei Kindern mit Dokumentation",
                     "value": 90.1,
                     "date": "2013",
                     "unit": "Anteil in %"
                  }
               ]
            }
         ]
      },
      {
         "name": "Versorgung",
         "values": [
            {
               "name": "Ambulant",
               "values": [
                  {
                     "name": "Ärzte",
                     "value": 198,
                     "date": "01.01.2015",
                     "unit": "EW je Arzt"
                  },
                  {
                     "name": "Hausärzte",
                     "value": 852,
                     "date": "01.01.2015",
                     "unit": "EW je Hausarzt"
                  },
                  {
                     "name": "Zahnärzte",
                     "value": 610,
                     "date": "31.12.2014",
                     "unit": "EW je Zahnarzt"
                  },
                  {
                     "name": "Psychotherapeut",
                     "value": 576,
                     "date": "2015",
                     "unit": "EW je Psychotherapeut"
                  }
               ]
            },
            {
               "name": "Stationär",
               "values": [
                  {
                     "name": "Krankenhausbetten",
                     "value": 7.1,
                     "date": "31.12.2014",
                     "unit": "je 100.000 EW"
                  }
               ]
            },
            {
               "name": "Pflegerisch",
               "values": [
                  {
                     "name": "Plätze in stationären Pflegeeinrichtungen",
                     "value": 2996,
                     "date": "15.12.2013",
                     "unit": "absolut"
                  },
                  {
                     "name": "Plätze in stationären Pflegeeinrichtungen",
                     "value": 4119.9,
                     "date": "15.12.2013",
                     "unit": "je 100.000 EW 65 J. u.ä."
                  }
               ]
            }
         ]
      }
   ]
}